idspiece/__init__.py
idspiece/cjk0.py
idspiece/cjk1.py
idspiece/cjk2.py
idspiece/cjk3.py
idspiece/idstable.py
idspiece-0.6.5.dist-info/LICENSE.txt
idspiece-0.6.5.dist-info/METADATA
idspiece-0.6.5.dist-info/WHEEL
idspiece-0.6.5.dist-info/top_level.txt
idspiece-0.6.5.dist-info/RECORD
