Metadata-Version: 2.1
Name: idspiece
Version: 0.6.5
Summary: Ideographic Tokenizer with CHISE-IDS
Home-page: https://github.com/KoichiYasuoka/IDSpiece
Author: Koichi Yasuoka
Author-email: yasuoka@kanji.zinbun.kyoto-u.ac.jp
License: GPL
Project-URL: CHISE, https://www.chise.org/ids/
Project-URL: Source, https://github.com/KoichiYasuoka/IDSpiece
Project-URL: Tracker, https://github.com/KoichiYasuoka/IDSpiece/issues
Keywords: NLP Chinese
Platform: UNKNOWN
Classifier: License :: OSI Approved :: GNU General Public License (GPL)
Classifier: Programming Language :: Python :: 3
Classifier: Operating System :: OS Independent
Classifier: Topic :: Text Processing :: Linguistic
Requires-Python: >=3.6
